workonsh/__init__.py
workonsh/main.py
workonsh/utils.py
workonsh-0.0.2.dist-info/METADATA
workonsh-0.0.2.dist-info/WHEEL
workonsh-0.0.2.dist-info/entry_points.txt
workonsh-0.0.2.dist-info/top_level.txt
workonsh-0.0.2.dist-info/RECORD
