Metadata-Version: 2.1
Name: workonsh
Version: 0.0.2
Summary: Work on a server
Author: Ngoc Bui
Author-email: ngocbh.pt@gmail.com
Project-URL: Bug Tracker, https://github.com/ngocbh/workonsh/issues
Project-URL: Documentation, https://github.com/ngocbh/workonsh/README.md
Project-URL: Source Code, https://github.com/ngocbh/workonsh
Requires-Python: >=3.6
Requires-Dist: click
